lib/__init__.py
lib/flask/API.py
lib/flask/__init__.py
lib/flask/database.py
lib/flask_jwt_extended/__init__.py
lib/flask_jwt_extended/main.py
lib/flask_jwt_extended/test.py
lib/qrcode/__init__.py
streamlit_extent-1.1.1.dist-info/METADATA
streamlit_extent-1.1.1.dist-info/WHEEL
streamlit_extent-1.1.1.dist-info/top_level.txt
streamlit_extent-1.1.1.dist-info/RECORD
